azurefunctions/__init__.py
azurefunctions/extensions/__init__.py
azurefunctions/extensions/mcp_server/__init__.py
azurefunctions/extensions/mcp_server/auth/__init__.py
azurefunctions/extensions/mcp_server/auth/provider_factory.py
azurefunctions/extensions/mcp_server/auth/token_handler.py
azurefunctions/extensions/mcp_server/core/__init__.py
azurefunctions/extensions/mcp_server/core/config_loader.py
azurefunctions/extensions/mcp_server/core/process_manager.py
azurefunctions/extensions/mcp_server/core/session_manager.py
azurefunctions/extensions/mcp_server/core/stdio_adapter.py
azurefunctions/extensions/mcp_server/decorators/__init__.py
azurefunctions/extensions/mcp_server/decorators/mcp_app.py
azurefunctions/extensions/mcp_server/models/__init__.py
azurefunctions/extensions/mcp_server/models/configuration.py
azurefunctions/extensions/mcp_server/models/enums.py
azurefunctions/extensions/mcp_server/utils/__init__.py
azurefunctions/extensions/mcp_server/utils/validation.py
azurefunctions_mcp_stdio_adapter-0.1.0a17.dist-info/METADATA
azurefunctions_mcp_stdio_adapter-0.1.0a17.dist-info/WHEEL
azurefunctions_mcp_stdio_adapter-0.1.0a17.dist-info/licenses/LICENSE
azurefunctions_mcp_stdio_adapter-0.1.0a17.dist-info/RECORD
