Metadata-Version: 2.4
Name: azurefunctions-mcp-stdio-adapter
Version: 0.1.0a17
Summary: Azure Functions Python extension for MCP STDIO adapter - converts STDIO MCP servers to streamable HTTP endpoints
Project-URL: Homepage, https://github.com/Azure/azure-functions-python-extensions
Project-URL: Repository, https://github.com/Azure/azure-functions-python-extensions.git
Project-URL: Documentation, https://docs.microsoft.com/azure/azure-functions/
Project-URL: Bug Reports, https://github.com/Azure/azure-functions-python-extensions/issues
Project-URL: Source Code, https://github.com/Azure/azure-functions-python-extensions/tree/main/azurefunctions-mcp-stdio-adapter
Project-URL: Changelog, https://github.com/Azure/azure-functions-python-extensions/blob/main/azurefunctions-mcp-stdio-adapter/CHANGELOG.md
Project-URL: Funding, https://github.com/sponsors/Azure
Author-email: Microsoft Corporation <azpysdkhelp@microsoft.com>
Maintainer-email: Microsoft Corporation <azpysdkhelp@microsoft.com>
License: MIT License
License-File: LICENSE
Keywords: authentication,azure,azure-ad,azure-functions,functions,mcp,model-context-protocol,oauth2,stdio
Classifier: Development Status :: 4 - Beta
Classifier: Environment :: Web Environment
Classifier: Framework :: AsyncIO
Classifier: Intended Audience :: Developers
Classifier: License :: OSI Approved :: MIT License
Classifier: Operating System :: OS Independent
Classifier: Programming Language :: Python :: 3
Classifier: Programming Language :: Python :: 3 :: Only
Classifier: Programming Language :: Python :: 3.11
Classifier: Programming Language :: Python :: 3.12
Classifier: Programming Language :: Python :: 3.13
Classifier: Topic :: Internet :: WWW/HTTP :: HTTP Servers
Classifier: Topic :: Security :: Cryptography
Classifier: Topic :: Software Development :: Libraries :: Python Modules
Classifier: Topic :: System :: Networking
Requires-Python: >=3.11
Requires-Dist: azure-functions<2.0.0,>=1.18.0
Requires-Dist: azure-identity<2.0.0,>=1.15.0
Requires-Dist: azurefunctions-extensions-base
Requires-Dist: azurefunctions-extensions-http-fastapi>=0.1.0
Requires-Dist: cryptography<43.0.0,>=41.0.0
Requires-Dist: mcp<2.0.0,>=1.0.0
Requires-Dist: pydantic<3.0.0,>=2.0.0
Requires-Dist: pyjwt<3.0.0,>=2.8.0
Requires-Dist: uv<1.0.0,>=0.8.0
Provides-Extra: auth
Requires-Dist: azure-identity<2.0.0,>=1.15.0; extra == 'auth'
Requires-Dist: cryptography<43.0.0,>=41.0.0; extra == 'auth'
Requires-Dist: pyjwt<3.0.0,>=2.8.0; extra == 'auth'
Provides-Extra: build
Requires-Dist: build<2.0.0,>=1.0.0; extra == 'build'
Requires-Dist: check-manifest<1.0,>=0.49; extra == 'build'
Requires-Dist: hatchling<2.0.0,>=1.18.0; extra == 'build'
Requires-Dist: setuptools<71.0.0,>=69.0.0; extra == 'build'
Requires-Dist: twine<6.0.0,>=4.0.0; extra == 'build'
Requires-Dist: wheel<1.0.0,>=0.42.0; extra == 'build'
Provides-Extra: dev
Requires-Dist: bandit<2.0.0,>=1.7.0; extra == 'dev'
Requires-Dist: black<25.0.0,>=24.0.0; extra == 'dev'
Requires-Dist: isort<6.0.0,>=5.13.0; extra == 'dev'
Requires-Dist: mypy<2.0.0,>=1.8.0; extra == 'dev'
Requires-Dist: pre-commit<4.0.0,>=3.6.0; extra == 'dev'
Requires-Dist: pytest-asyncio<1.0.0,>=0.23.0; extra == 'dev'
Requires-Dist: pytest-cov<5.0.0,>=4.1.0; extra == 'dev'
Requires-Dist: pytest-mock<4.0.0,>=3.12.0; extra == 'dev'
Requires-Dist: pytest<9.0.0,>=8.0.0; extra == 'dev'
Requires-Dist: ruff<1.0.0,>=0.2.0; extra == 'dev'
Provides-Extra: docs
Requires-Dist: myst-parser<4.0.0,>=2.0.0; extra == 'docs'
Requires-Dist: sphinx-autodoc-typehints<3.0.0,>=1.25.0; extra == 'docs'
Requires-Dist: sphinx-rtd-theme<3.0.0,>=2.0.0; extra == 'docs'
Requires-Dist: sphinx<8.0.0,>=7.0.0; extra == 'docs'
Provides-Extra: test
Requires-Dist: httpx<1.0.0,>=0.26.0; extra == 'test'
Requires-Dist: pytest-asyncio<1.0.0,>=0.23.0; extra == 'test'
Requires-Dist: pytest-cov<5.0.0,>=4.1.0; extra == 'test'
Requires-Dist: pytest-mock<4.0.0,>=3.12.0; extra == 'test'
Requires-Dist: pytest<9.0.0,>=8.0.0; extra == 'test'
Requires-Dist: responses<1.0.0,>=0.24.0; extra == 'test'
